{
  "feature_id": "base_create_query_hop2",
  "canonical_id": "base_create_query_hop2",
  "task": "hotpotqa_context",
  "target_module": "create_query_hop2",
  "requires": ["_section_create_query_hop2"],
  "conflicts_with": [],
  "primitive_edits": [
    {
      "func_type": "insert_node",
      "params": {
        "node_type": "rule",
        "parent_id": "f84c4068e433",
        "payload": {
          "content": "Write one focused retrieval query for the missing second-hop evidence, using the question and first-hop summary."
        }
      }
    }
  ],
  "rationale": "Base instruction for the second-hop query generation module."
}
