{
  "feature_id": "enable_sql",
  "canonical_id": "enable_sql",
  "task": "table_qa",
  "requires": ["_section_strategy"],
  "conflicts_with": ["enable_code", "enable_cot"],
  "primitive_edits": [
    {
      "func_type": "insert_node",
      "params": {
        "node_type": "rule",
        "parent_id": "d1ca7abe1430",
        "payload": {"content": "Write a single SQL query against table `t`. The table has the columns shown in the input header. Do NOT use any table name other than `t`. Do NOT define schemas, views, or CTEs that reference other names."}
      }
    },
    {
      "func_type": "insert_node",
      "params": {
        "node_type": "rule",
        "parent_id": "d1ca7abe1430",
        "payload": {"content": "Example — for the question 'Who scored the most points?' on a table with columns [Position, Driver, Team, Points]:\n```sql\nSELECT Driver FROM t ORDER BY CAST(Points AS INTEGER) DESC LIMIT 1;\n```"}
      }
    },
    {
      "func_type": "insert_node",
      "params": {
        "node_type": "output_field",
        "parent_id": "__root__",
        "payload": {"name": "sql", "description": "SQL query that answers the question."}
      }
    },
    {
      "func_type": "set_format",
      "params": {"style": "code_block"}
    }
  ]
}
